paperplane/__init__.py
paperplane/backends/__init__.py
paperplane/backends/click/__init__.py
paperplane/backends/click/choice.py
paperplane/backends/click/echo.py
paperplane/backends/click/int.py
paperplane/backends/click/str.py
paperplane/cli/__init__.py
paperplane/cli/parser.py
paperplane/exceptions/__init__.py
paperplane/parser/__init__.py
paperplane/parser/config.py
paperplane/parser/macros.py
paperplane/parser/main.py
paperplane-0.0.3.dist-info/LICENSE
paperplane-0.0.3.dist-info/METADATA
paperplane-0.0.3.dist-info/WHEEL
paperplane-0.0.3.dist-info/entry_points.txt
paperplane-0.0.3.dist-info/top_level.txt
paperplane-0.0.3.dist-info/RECORD
