Metadata-Version: 2.1
Name: paperplane
Version: 0.0.3
Summary: A simple interactive CLI builder
Home-page: https://github.com/abhilash1in/paperplane
Author: Abhilash Kishore
Author-email: abhilash1in@gmail.com
License: MIT
Platform: UNKNOWN
Classifier: Programming Language :: Python :: 3
Classifier: License :: OSI Approved :: MIT License
Classifier: Operating System :: OS Independent
Requires-Python: >=3.6
Requires-Dist: pyyaml
Requires-Dist: click
Requires-Dist: colorama
Provides-Extra: docs
Requires-Dist: sphinx ; extra == 'docs'
Requires-Dist: sphinx-rtd-theme ; extra == 'docs'
Requires-Dist: recommonmark ; extra == 'docs'
